sora_ai_video/__init__.py
sora_ai_video-1767580.963.83.dist-info/licenses/LICENSE
sora_ai_video-1767580.963.83.dist-info/METADATA
sora_ai_video-1767580.963.83.dist-info/WHEEL
sora_ai_video-1767580.963.83.dist-info/top_level.txt
sora_ai_video-1767580.963.83.dist-info/RECORD
